oshino_statsd/__init__.py
oshino_statsd/agent.py
oshino_statsd/receiver.py
oshino_statsd/version.py
oshino_statsd-0.1.4.dist-info/DESCRIPTION.rst
oshino_statsd-0.1.4.dist-info/METADATA
oshino_statsd-0.1.4.dist-info/RECORD
oshino_statsd-0.1.4.dist-info/WHEEL
oshino_statsd-0.1.4.dist-info/metadata.json
oshino_statsd-0.1.4.dist-info/top_level.txt
