Metadata-Version: 2.0
Name: oshino-statsd
Version: 0.1.4
Summary: ...
Home-page: UNKNOWN
Author: zaibacu
Author-email: UNKNOWN
License: UNKNOWN
Platform: UNKNOWN
Requires-Dist: oshino (>=0.1.3)
